libname/__init__.py
libname/useit.py
useit-0.0.1.dist-info/METADATA
useit-0.0.1.dist-info/WHEEL
useit-0.0.1.dist-info/top_level.txt
useit-0.0.1.dist-info/RECORD
