Metadata-Version: 2.1
Name: useit
Version: 0.0.1
Summary: Premade Cool Python Codes
Author: Aarush Mehta
Author-email: <aarush07codec@gmail.com>
Keywords: python,python3,autocode,premade code,code,programming
Classifier: Development Status :: 1 - Planning
Classifier: Intended Audience :: Developers
Classifier: Programming Language :: Python :: 3
Classifier: Operating System :: Unix
Classifier: Operating System :: MacOS :: MacOS X
Classifier: Operating System :: Microsoft :: Windows
Requires-Dist: webbrowser
Requires-Dist: pynotifier
Requires-Dist: pyautogui
Requires-Dist: psutil
Requires-Dist: pywhatkit
Requires-Dist: wikipedia
